<?xml version="1.0" encoding="utf-8" ?>
<odoo>

    <record id="product_template_tree_view_inherit" model="ir.ui.view">
        <field name="name">product.template.tree.view.inherit</field>
        <field name="model">product.template</field>
        <field name="priority">20</field>
        <field name="inherit_id" ref="product.product_template_tree_view"/>
        <field name="arch" type="xml">
            <xpath expr="//tree" postion="inside">
                <field name="form_id" optional="hide"/>
                <field name="material_id" optional="hide"/>
                <field name="licence_id" optional="hide"/>
                <field name="brand_id" optional="hide"/>
                <field name="collection_id" optional="hide"/>
                <field name="device_id" optional="hide"/>
                <field name="color_id" optional="hide"/>
            </xpath>

            <field name="standard_price" position="attributes">
                <attribute name="readonly">0</attribute>
            </field>

            <field name="default_code" position="attributes">
                <attribute name="readonly">1</attribute>
            </field>
            <field name="default_code" position="attributes">
                <attribute name="string">SKU Code</attribute>
            </field>
            <field name="barcode" position="attributes">
                <attribute name="string">EAN Code</attribute>
            </field>
            <field name="categ_id" position="attributes">
                <attribute name="string">Family</attribute>
            </field>
            <field name="responsible_id" position="attributes">
                <attribute name="optional">show</attribute>
            </field>

        </field>
    </record>

    <record id="product_template_search_view_inherit" model="ir.ui.view">
        <field name="name">product.template.search.view.inherit</field>
        <field name="model">product.template</field>
        <field name="inherit_id" ref="product.product_template_search_view"/>
        <field name="arch" type="xml">
            <field name="categ_id" position="after">
                <field name="form_id"/>
                <field name="material_id"/>
                <field name="licence_id"/>
                <field name="brand_id"/>
                <field name="collection_id"/>
                <field name="device_id"/>
                <field name="color_id"/>
            </field>
            <field name="categ_id" position="attributes">
                <attribute name="string">Product Family</attribute>
            </field>
            <filter name="categ_id" position="attributes">
                <attribute name="string">Product Family</attribute>
            </filter>
            <xpath expr="//group" position="inside">
                <filter string="Product Form" name="filter_product_form" context="{'group_by': 'form_id'}"/>
                <filter string="Product Material" name="filter_product_material" context="{'group_by': 'material_id'}"/>
                <filter string="Product Licence" name="filter_product_licence" context="{'group_by': 'licence_id'}"/>
                <filter string="Device" name="filter_product_device" context="{'group_by': 'device_id'}"/>
                <filter string="Product Collection" name="filter_product_collection" context="{'group_by': 'collection_id'}"/>
                <filter string="Product Brand" name="filter_product_brand" context="{'group_by': 'brand_id'}"/>
                <filter string="Product Color" name="filter_product_color" context="{'group_by': 'color_id'}"/>
            </xpath>
        </field>
    </record>

    <record id="product_template_only_form_view_inherit" model="ir.ui.view">
        <field name="name">product.template.only.form.view.inherit</field>
        <field name="model">product.template</field>
        <field name="inherit_id" ref="product.product_template_only_form_view"/>
        <field name="priority">100</field>
        <field name="arch" type="xml">

            <field name="barcode" position="replace"/>
            <field name="categ_id" position="replace"/>

            <xpath expr="//page[@name='general_information']//group" position="inside">
                <group>
                    <field name="barcode" string="EAN Code"/>
                    <field name="product_type_product"/>
                    <field name="royalties_margins"/>
                </group>
            </xpath>

            <xpath expr="//page[@name='general_information']//group" position="inside">
                <group>
                    <field name="categ_id" string="Family"/>
                    <field name="form_id"/>
                    <field name="material_id"/>
                    <field name="color_id"/>
                    <field name="licence_id"/>
                    <field name="brand_id"/>
                    <field name="collection_id"/>
                    <field name="device_id"/>
                </group>
            </xpath>

        </field>
    </record>

</odoo>